gridstatus/__init__.py
gridstatus/base.py
gridstatus/decorators.py
gridstatus/eia.py
gridstatus/eia_constants.py
gridstatus/ercot.py
gridstatus/ercot_60d_utils.py
gridstatus/ercot_constants.py
gridstatus/gs_logging.py
gridstatus/ieso.py
gridstatus/ieso_constants.py
gridstatus/isone.py
gridstatus/lmp_config.py
gridstatus/miso.py
gridstatus/miso_api.py
gridstatus/nyiso.py
gridstatus/pjm.py
gridstatus/pjm_constants.py
gridstatus/py.typed
gridstatus/spp.py
gridstatus/test.py
gridstatus/utils.py
gridstatus/version.py
gridstatus/viz.py
gridstatus/aeso/__init__.py
gridstatus/aeso/aeso.py
gridstatus/aeso/aeso_constants.py
gridstatus/caiso/__init__.py
gridstatus/caiso/caiso.py
gridstatus/caiso/caiso_constants.py
gridstatus/caiso/caiso_utils.py
gridstatus/eia_data/grid_monitor_files.json
gridstatus/ercot_api/README.md
gridstatus/ercot_api/__init__.py
gridstatus/ercot_api/api_parser.py
gridstatus/ercot_api/ercot_api.py
gridstatus/ercot_api/esrapi-apim-api.json
gridstatus/ercot_api/pubapi-apim-api.json
gridstatus/isone_api/isone_api.py
gridstatus/isone_api/isone_api_constants.py
gridstatus/public_certificates/ieso/intermediate_and_root.pem
gridstatus/public_certificates/miso_api/intermediate_and_root.pem
gridstatus/tests/__init__.py
gridstatus/tests/base_test_iso.py
gridstatus/tests/conftest.py
gridstatus/tests/decorators.py
gridstatus/tests/test_base.py
gridstatus/tests/test_decorators.py
gridstatus/tests/test_logger.py
gridstatus/tests/test_utils.py
gridstatus/tests/test_version.py
gridstatus/tests/test_viz.py
gridstatus/tests/vcr_utils.py
gridstatus/tests/fixtures/pjm/pjm_5min_solar_forecast_response.json
gridstatus/tests/fixtures/spp/grid-conditions-20210215.html
gridstatus/tests/fixtures/spp/grid-conditions-20210217.html
gridstatus/tests/fixtures/spp/grid-conditions-20221010.html
gridstatus/tests/fixtures/spp/grid-conditions-20230101.html
gridstatus/tests/source_specific/test_aeso.py
gridstatus/tests/source_specific/test_caiso.py
gridstatus-0.34.0.dist-info/METADATA
gridstatus-0.34.0.dist-info/WHEEL
gridstatus-0.34.0.dist-info/licenses/LICENSE
gridstatus-0.34.0.dist-info/RECORD
