Metadata-Version: 2.4
Name: gridstatus
Version: 0.34.0
Summary: API to access energy data
Project-URL: Source Code, https://github.com/gridstatus/gridstatus/
Project-URL: Changes, https://github.com/gridstatus/gridstatus/blob/main/CHANGELOG.md
Project-URL: Issue Tracker, https://github.com/gridstatus/gridstatus/issues
Author-email: Max Kanter <kmax12@gmail.com>, Will Koehrsen <will@gridstatus.com>, Ryan Kladar <ryan@gridstatus.com>
License: Copyright 2022 James Max Kanter
License-File: LICENSE
Keywords: energy,independent system operator
Requires-Python: <3.13,>=3.10
Requires-Dist: beautifulsoup4>=4.8.13
Requires-Dist: certifi>=2024.7.4
Requires-Dist: cryptography>=43.0.1
Requires-Dist: frozendict>=2.4.6
Requires-Dist: lxml>=5.3.0
Requires-Dist: openpyxl>=3.1.0
Requires-Dist: pandas>=2.2.1
Requires-Dist: pdfplumber>=0.11.5
Requires-Dist: plotly>=5.11.0
Requires-Dist: requests>=2.32.2
Requires-Dist: setuptools>=70.0.0
Requires-Dist: tabulate>=0.9.0
Requires-Dist: termcolor>=2.2.0
Requires-Dist: tqdm>=4.64.1
Requires-Dist: urllib3>=2.2.2
Requires-Dist: virtualenv>=20.26.6
Requires-Dist: xlrd>=2.0.1
Requires-Dist: xmltodict>=0.14.2
Requires-Dist: zipp>=3.19.1
